gatum_api_py/GatumAPI.py
gatum_api_py/__init__.py
gatum_api_py-1.0.2.dist-info/LICENSE
gatum_api_py-1.0.2.dist-info/METADATA
gatum_api_py-1.0.2.dist-info/WHEEL
gatum_api_py-1.0.2.dist-info/top_level.txt
gatum_api_py-1.0.2.dist-info/RECORD
