Metadata-Version: 2.1
Name: gatum-api-py
Version: 1.0.2
Summary: Python library for interacting with Gatum GET API
Download-URL: https://github.com/Sempico/gatum-api-py
Author: Sempico Solutions Group LTD
Author-email: support@sempico.solutions
License: MIT License
Classifier: Development Status :: 4 - Beta
Classifier: Intended Audience :: Developers
Classifier: License :: OSI Approved :: MIT License
Classifier: Operating System :: OS Independent
Classifier: Programming Language :: Python
Classifier: Programming Language :: Python :: 3
Classifier: Programming Language :: Python :: 3.10
License-File: LICENSE
Requires-Dist: requests
